bcijelly/__init__.py
bcijelly/exanple.py
bcijelly-0.0.2.dist-info/licenses/LICENSE
bcijelly-0.0.2.dist-info/METADATA
bcijelly-0.0.2.dist-info/WHEEL
bcijelly-0.0.2.dist-info/top_level.txt
bcijelly-0.0.2.dist-info/RECORD
