Metadata-Version: 2.4
Name: bcijelly
Version: 0.0.2
Summary: BCI utilities and models
Author-email: Liyuan Han <hanliyuan@ion.ac.cn>
License-Expression: MIT
Classifier: Programming Language :: Python :: 3
Classifier: Operating System :: OS Independent
Requires-Python: >=3.9
License-File: LICENSE
Dynamic: license-file
